CHANGELOG.rst
LICENSE
MANIFEST.in
README.rst
setup.py
django_ripple_api.egg-info/PKG-INFO
django_ripple_api.egg-info/SOURCES.txt
django_ripple_api.egg-info/dependency_links.txt
django_ripple_api.egg-info/requires.txt
django_ripple_api.egg-info/top_level.txt
ripple_api/__init__.py
ripple_api/admin.py
ripple_api/models.py
ripple_api/ripple_api.py
ripple_api/signals.py
ripple_api/tasks.py
ripple_api/test_api.py
ripple_api/test_balance.py
ripple_api/test_is_trust.py
ripple_api/test_trade.py
ripple_api/test_trust.py
ripple_api/trade.py
ripple_api/utils.py
ripple_api/views.py
ripple_api/management/__init__.py
ripple_api/management/transaction_processors.py
ripple_api/management/commands/__init__.py
ripple_api/management/commands/process_transactions.py
ripple_api/migrations/0001_initial.py
ripple_api/migrations/__init__.py