Metadata-Version: 1.1
Name: django-ripple-api
Version: 0.0.48
Summary: Python wrapper for the Ripple API
Home-page: https://github.com/42cc/ripple_api
Author: 42 Coffee Cups
Author-email: contact@42cc.co
License: BSD License
Download-URL: https://github.com/42cc/ripple_api/archive/master.zip
Keywords: ripple,api
Platform: UNKNOWN
Classifier: Environment :: Web Environment
Classifier: Intended Audience :: Developers
Classifier: License :: OSI Approved :: BSD License
Classifier: Programming Language :: Python
Requires: python (>= 2.7)
Requires: requests
Requires: django_model_utils
